MANIFEST.in
README.md
setup.cfg
setup.py
versioneer.py
bmlx_openapi_client/__init__.py
bmlx_openapi_client/_version.py
bmlx_openapi_client/api-server
bmlx_openapi_client/api_client.py
bmlx_openapi_client/configuration.py
bmlx_openapi_client/dummy_server.py
bmlx_openapi_client/exceptions.py
bmlx_openapi_client/rest.py
bmlx_openapi_client.egg-info/PKG-INFO
bmlx_openapi_client.egg-info/SOURCES.txt
bmlx_openapi_client.egg-info/dependency_links.txt
bmlx_openapi_client.egg-info/not-zip-safe
bmlx_openapi_client.egg-info/requires.txt
bmlx_openapi_client.egg-info/top_level.txt
bmlx_openapi_client/api/__init__.py
bmlx_openapi_client/api/artifact_api.py
bmlx_openapi_client/api/auth_api.py
bmlx_openapi_client/api/component_run_api.py
bmlx_openapi_client/api/deployment_api.py
bmlx_openapi_client/api/execution_event_api.py
bmlx_openapi_client/api/experiment_api.py
bmlx_openapi_client/api/experiment_run_api.py
bmlx_openapi_client/api/experiment_version_api.py
bmlx_openapi_client/api/group_api.py
bmlx_openapi_client/api/model_api.py
bmlx_openapi_client/api/model_suite_api.py
bmlx_openapi_client/api/pipeline_api.py
bmlx_openapi_client/api/pipeline_version_api.py
bmlx_openapi_client/api/user_api.py
bmlx_openapi_client/models/__init__.py
bmlx_openapi_client/models/artifact.py
bmlx_openapi_client/models/component_run.py
bmlx_openapi_client/models/deployment.py
bmlx_openapi_client/models/error_response.py
bmlx_openapi_client/models/execution_event.py
bmlx_openapi_client/models/experiment.py
bmlx_openapi_client/models/experiment_run.py
bmlx_openapi_client/models/experiment_run_summary.py
bmlx_openapi_client/models/experiment_version.py
bmlx_openapi_client/models/get_artifacts_response.py
bmlx_openapi_client/models/get_component_runs_response.py
bmlx_openapi_client/models/get_deployments_response.py
bmlx_openapi_client/models/get_execution_events_response.py
bmlx_openapi_client/models/get_experiment_runs_response.py
bmlx_openapi_client/models/get_experiments_response.py
bmlx_openapi_client/models/get_groups_response.py
bmlx_openapi_client/models/get_model_suites_response.py
bmlx_openapi_client/models/get_models_response.py
bmlx_openapi_client/models/get_pipeline_versions_response.py
bmlx_openapi_client/models/get_pipelines_response.py
