Metadata-Version: 1.0
Name: bmlx-openapi-client
Version: 0.0.90.3
Summary: bmlx api-server.
Home-page: UNKNOWN
Author: OpenAPI Generator community
Author-email: team@openapitools.org
License: Apache 2.0
Keywords: OpenAPI,OpenAPI-Generator,bmlx api-server.
Platform: UNKNOWN
